{
  "type": "Feature",
  "properties": {
    "iso:country":"BG",
    "sg:address":"6, Ravnishta str.",
    "sg:city":"Plovdiv",
    "sg:classifiers":[
        {
            "category":"Professional",
            "subcategory":"Computer Services",
            "type":"Services"
        }
    ],
    "sg:postcode":"4001",
    "sg:tags":[
        "wordframe",
        "social-media",
        "social-media-application",
        "collaboration-software",
        "social-networking",
        "blogs",
        "wiki",
        "rss",
        "rss-aggregator",
        "corporate-blogging",
        "content-management",
        "online-publishing",
        "ecm",
        "wcm",
        "enterprise-content-management",
        "web-content-management",
        "blo"
    ],
    "sg:website":"http://wordframe.com",
    "wof:name":"ITBrix",
    "wof:placetype":"venue"
},
  "geometry": {"coordinates":[24.714267,42.133978],"type":"Point"}
}