{
  "type": "Feature",
  "properties": {
    "iso:country":"BG",
    "sg:address":"14 Trepetlika Str. ent. 1, apt. 9",
    "sg:city":"Sofia",
    "sg:classifiers":[
        {
            "category":"Professional",
            "subcategory":"Computer Services",
            "type":"Services"
        }
    ],
    "sg:postcode":"1407",
    "sg:tags":[
        "visual-similarity",
        "image-search",
        "auto-tagging",
        "stock-photo",
        "stock-photography",
        "facebook",
        "photobucket",
        "advertising"
    ],
    "sg:website":"http://www.imagga.com",
    "wof:name":"Imagga",
    "wof:placetype":"venue"
},
  "geometry": {"coordinates":[23.3237457,42.6703475],"type":"Point"}
}